{"general": {"id": 457705, "fullName": "Andrew McCutchen", "firstName": "Andrew", "lastName": "McCutchen", "primaryNumber": "22", "currentTeam": {"id": 134}, "primaryPosition": {"code": "7", "abbreviation": "LF"}, "useName": "Andrew", "boxscoreName": "McCutchen", "nickName": "Drusneeze", "mlbDebutDate": "2009-06-04", "nameFirstLast": "Andrew McCutchen", "firstLastName": "Andrew McCutchen", "lastFirstName": "McCutchen, Andrew", "lastInitName": "McCutchen, A", "initLastName": "A McCutchen", "fullFMLName": "Andrew Stefan McCutchen", "fullLFMName": "McCutchen, Andrew Stefan"}, "stats": {"id": 457705, "first_name": "Andrew", "last_name": "McCutchen", "active": true, "current_team": "Pittsburgh Pirates", "position": "LF", "nickname": "Drusneeze", "last_played": null, "mlb_debut": "2009-06-04", "bat_side": "Right", "pitch_hand": "Right", "stats": [{"type": "career", "group": "hitting", "season": null, "stats": {"gamesPlayed": 1895, "groundOuts": 1659, "airOuts": 1955, "runs": 1118, "doubles": 392, "triples": 49, "homeRuns": 287, "strikeOuts": 1542, "baseOnBalls": 983, "intentionalWalks": 67, "hits": 1948, "hitByPitch": 81, "avg": ".277", "atBats": 7035, "obp": ".369", "slg": ".469", "ops": ".838", "caughtStealing": 84, "stolenBases": 205, "stolenBasePercentage": ".709", "groundIntoDoublePlay": 118, "numberOfPitches": 33126, "plateAppearances": 8168, "totalBases": 3299, "rbi": 1002, "leftOnBase": 2532, "sacBunts": 3, "sacFlies": 66, "babip": ".315", "groundOutsToAirouts": "0.85", "catchersInterference": 0, "atBatsPerHomeRun": "24.51"}}, {"type": "career", "group": "fielding", "season": null, "stats": {"gamesPlayed": 1332, "gamesStarted": 1322, "assists": 63, "putOuts": 2959, "errors": 37, "chances": 3059, "fielding": ".988", "position": {"code": "8", "name": "Outfielder", "type": "Outfielder", "abbreviation": "CF"}, "rangeFactorPerGame": "2.27", "rangeFactorPer9Inn": "2.34", "innings": "11612.0", "games": 1332, "doublePlays": 16, "triplePlays": 0, "throwingErrors": 9}}, {"type": "career", "group": "fielding", "season": null, "stats": {"gamesPlayed": 175, "gamesStarted": 171, "assists": 10, "putOuts": 312, "errors": 2, "chances": 324, "fielding": ".994", "position": {"code": "9", "name": "Outfielder", "type": "Outfielder", "abbreviation": "RF"}, "rangeFactorPerGame": "1.84", "rangeFactorPer9Inn": "1.92", "innings": "1512.0", "games": 175, "doublePlays": 1, "triplePlays": 0, "throwingErrors": 0}}, {"type": "career", "group": "fielding", "season": null, "stats": {"gamesPlayed": 108, "gamesStarted": 108, "assists": 0, "putOuts": 0, "errors": 0, "chances": 0, "fielding": ".000", "position": {"code": "10", "name": "Designated Hitter", "type": "Hitter", "abbreviation": "DH"}, "rangeFactorPerGame": "0.00", "rangeFactorPer9Inn": "-.--", "innings": "0.0", "games": 108, "doublePlays": 0, "triplePlays": 0, "throwingErrors": 0}}, {"type": "career", "group": "fielding", "season": null, "stats": {"gamesPlayed": 269, "gamesStarted": 254, "assists": 6, "putOuts": 385, "errors": 5, "chances": 396, "fielding": ".987", "position": {"code": "7", "name": "Outfielder", "type": "Outfielder", "abbreviation": "LF"}, "rangeFactorPerGame": "1.45", "rangeFactorPer9Inn": "1.63", "innings": "2161.2", "games": 269, "doublePlays": 0, "triplePlays": 0, "throwingErrors": 1}}, {"type": "yearByYear", "group": "hitting", "season": "2009", "stats": {"gamesPlayed": 108, "groundOuts": 104, "airOuts": 126, "runs": 74, "doubles": 26, "triples": 9, "homeRuns": 12, "strikeOuts": 83, "baseOnBalls": 54, "intentionalWalks": 2, "hits": 124, "hitByPitch": 2, "avg": ".286", "atBats": 433, "obp": ".365", "slg": ".471", "ops": ".836", "caughtStealing": 5, "stolenBases": 22, "stolenBasePercentage": ".815", "groundIntoDoublePlay": 3, "numberOfPitches": 2007, "plateAppearances": 493, "totalBases": 204, "rbi": 54, "leftOnBase": 106, "sacBunts": 0, "sacFlies": 4, "babip": ".327", "groundOutsToAirouts": "0.83", "catchersInterference": 0, "atBatsPerHomeRun": "36.08"}}, {"type": "yearByYear", "group": "hitting", "season": "2010", "stats": {"gamesPlayed": 154, "groundOuts": 152, "airOuts": 174, "runs": 94, "doubles": 35, "triples": 5, "homeRuns": 16, "strikeOuts": 89, "baseOnBalls": 70, "intentionalWalks": 1, "hits": 163, "hitByPitch": 5, "avg": ".286", "atBats": 570, "obp": ".365", "slg": ".449", "ops": ".814", "caughtStealing": 10, "stolenBases": 33, "stolenBasePercentage": ".767", "groundIntoDoublePlay": 6, "numberOfPitches": 2632, "plateAppearances": 653, "totalBases": 256, "rbi": 56, "leftOnBase": 148, "sacBunts": 1, "sacFlies": 7, "babip": ".311", "groundOutsToAirouts": "0.87", "catchersInterference": 0, "atBatsPerHomeRun": "35.62"}}, {"type": "yearByYear", "group": "hitting", "season": "2011", "stats": {"gamesPlayed": 158, "groundOuts": 135, "airOuts": 171, "runs": 87, "doubles": 34, "triples": 5, "homeRuns": 23, "strikeOuts": 126, "baseOnBalls": 89, "intentionalWalks": 3, "hits": 148, "hitByPitch": 9, "avg": ".259", "atBats": 572, "obp": ".364", "slg": ".456", "ops": ".820", "caughtStealing": 10, "stolenBases": 23, "stolenBasePercentage": ".697", "groundIntoDoublePlay": 7, "numberOfPitches": 2832, "plateAppearances": 678, "totalBases": 261, "rbi": 89, "leftOnBase": 196, "sacBunts": 2, "sacFlies": 6, "babip": ".291", "groundOutsToAirouts": "0.79", "catchersInterference": 0, "atBatsPerHomeRun": "24.87"}}, {"type": "yearByYear", "group": "hitting", "season": "2012", "stats": {"gamesPlayed": 157, "groundOuts": 134, "airOuts": 138, "runs": 107, "doubles": 29, "triples": 6, "homeRuns": 31, "strikeOuts": 132, "baseOnBalls": 70, "intentionalWalks": 13, "hits": 194, "hitByPitch": 5, "avg": ".327", "atBats": 593, "obp": ".400", "slg": ".553", "ops": ".953", "caughtStealing": 12, "stolenBases": 20, "stolenBasePercentage": ".625", "groundIntoDoublePlay": 9, "numberOfPitches": 2612, "plateAppearances": 673, "totalBases": 328, "rbi": 96, "leftOnBase": 212, "sacBunts": 0, "sacFlies": 5, "babip": ".375", "groundOutsToAirouts": "0.97", "catchersInterference": 0, "atBatsPerHomeRun": "19.13"}}, {"type": "yearByYear", "group": "hitting", "season": "2013", "stats": {"gamesPlayed": 157, "groundOuts": 133, "airOuts": 168, "runs": 97, "doubles": 38, "triples": 5, "homeRuns": 21, "strikeOuts": 101, "baseOnBalls": 78, "intentionalWalks": 12, "hits": 185, "hitByPitch": 9, "avg": ".317", "atBats": 583, "obp": ".404", "slg": ".508", "ops": ".912", "caughtStealing": 10, "stolenBases": 27, "stolenBasePercentage": ".730", "groundIntoDoublePlay": 13, "numberOfPitches": 2562, "plateAppearances": 674, "totalBases": 296, "rbi": 84, "leftOnBase": 238, "sacBunts": 0, "sacFlies": 4, "babip": ".353", "groundOutsToAirouts": "0.79", "catchersInterference": 0, "atBatsPerHomeRun": "27.76"}}, {"type": "yearByYear", "group": "hitting", "season": "2014", "stats": {"gamesPlayed": 146, "groundOuts": 118, "airOuts": 149, "runs": 89, "doubles": 38, "triples": 6, "homeRuns": 25, "strikeOuts": 115, "baseOnBalls": 84, "intentionalWalks": 8, "hits": 172, "hitByPitch": 10, "avg": ".314", "atBats": 548, "obp": ".410", "slg": ".542", "ops": ".952", "caughtStealing": 3, "stolenBases": 18, "stolenBasePercentage": ".857", "groundIntoDoublePlay": 9, "numberOfPitches": 2640, "plateAppearances": 648, "totalBases": 297, "rbi": 83, "leftOnBase": 214, "sacBunts": 0, "sacFlies": 6, "babip": ".355", "groundOutsToAirouts": "0.79", "catchersInterference": 0, "atBatsPerHomeRun": "21.92"}}, {"type": "yearByYear", "group": "hitting", "season": "2015", "stats": {"gamesPlayed": 157, "groundOuts": 122, "airOuts": 155, "runs": 91, "doubles": 36, "triples": 3, "homeRuns": 23, "strikeOuts": 133, "baseOnBalls": 98, "intentionalWalks": 12, "hits": 165, "hitByPitch": 12, "avg": ".292", "atBats": 566, "obp": ".401", "slg": ".488", "ops": ".889", "caughtStealing": 5, "stolenBases": 11, "stolenBasePercentage": ".688", "groundIntoDoublePlay": 9, "numberOfPitches": 2780, "plateAppearances": 685, "totalBases": 276, "rbi": 96, "leftOnBase": 202, "sacBunts": 0, "sacFlies": 9, "babip": ".339", "groundOutsToAirouts": "0.79", "catchersInterference": 0, "atBatsPerHomeRun": "24.61"}}, {"type": "yearByYear", "group": "hitting", "season": "2016", "stats": {"gamesPlayed": 153, "groundOuts": 126, "airOuts": 179, "runs": 81, "doubles": 26, "triples": 3, "homeRuns": 24, "strikeOuts": 143, "baseOnBalls": 69, "intentionalWalks": 7, "hits": 153, "hitByPitch": 5, "avg": ".256", "atBats": 598, "obp": ".336", "slg": ".430", "ops": ".766", "caughtStealing": 7, "stolenBases": 6, "stolenBasePercentage": ".462", "groundIntoDoublePlay": 15, "numberOfPitches": 2740, "plateAppearances": 675, "totalBases": 257, "rbi": 79, "leftOnBase": 240, "sacBunts": 0, "sacFlies": 3, "babip": ".297", "groundOutsToAirouts": "0.70", "catchersInterference": 0, "atBatsPerHomeRun": "24.92"}}, {"type": "yearByYear", "group": "hitting", "season": "2017", "stats": {"gamesPlayed": 156, "groundOuts": 144, "airOuts": 154, "runs": 94, "doubles": 30, "triples": 2, "homeRuns": 28, "strikeOuts": 116, "baseOnBalls": 73, "intentionalWalks": 5, "hits": 159, "hitByPitch": 4, "avg": ".279", "atBats": 570, "obp": ".363", "slg": ".486", "ops": ".849", "caughtStealing": 5, "stolenBases": 11, "stolenBasePercentage": ".688", "groundIntoDoublePlay": 10, "numberOfPitches": 2621, "plateAppearances": 650, "totalBases": 277, "rbi": 88, "leftOnBase": 223, "sacBunts": 0, "sacFlies": 3, "babip": ".305", "groundOutsToAirouts": "0.94", "catchersInterference": 0, "atBatsPerHomeRun": "20.36"}}, {"type": "yearByYear", "group": "hitting", "season": "2018", "stats": {"gamesPlayed": 130, "groundOuts": 118, "airOuts": 124, "runs": 65, "doubles": 28, "triples": 2, "homeRuns": 15, "strikeOuts": 123, "baseOnBalls": 73, "intentionalWalks": 1, "hits": 123, "hitByPitch": 7, "avg": ".255", "atBats": 482, "obp": ".357", "slg": ".415", "ops": ".772", "caughtStealing": 6, "stolenBases": 13, "stolenBasePercentage": ".684", "groundIntoDoublePlay": 11, "numberOfPitches": 2387, "plateAppearances": 568, "totalBases": 200, "rbi": 55, "leftOnBase": 180, "sacBunts": 0, "sacFlies": 6, "babip": ".309", "groundOutsToAirouts": "0.95", "catchersInterference": 0, "atBatsPerHomeRun": "32.13"}}, {"type": "yearByYear", "group": "hitting", "season": "2018", "stats": {"gamesPlayed": 25, "groundOuts": 22, "airOuts": 22, "runs": 18, "doubles": 2, "triples": 1, "homeRuns": 5, "strikeOuts": 22, "baseOnBalls": 22, "intentionalWalks": 0, "hits": 22, "hitByPitch": 4, "avg": ".253", "atBats": 87, "obp": ".421", "slg": ".471", "ops": ".892", "caughtStealing": 3, "stolenBases": 1, "stolenBasePercentage": ".250", "groundIntoDoublePlay": 1, "numberOfPitches": 502, "plateAppearances": 114, "totalBases": 41, "rbi": 10, "leftOnBase": 22, "sacBunts": 0, "sacFlies": 1, "babip": ".279", "groundOutsToAirouts": "1.00", "catchersInterference": 0, "atBatsPerHomeRun": "17.40"}}, {"type": "yearByYear", "group": "hitting", "season": "2018", "stats": {"gamesPlayed": 155, "groundOuts": 140, "airOuts": 146, "runs": 83, "doubles": 30, "triples": 3, "homeRuns": 20, "strikeOuts": 145, "baseOnBalls": 95, "intentionalWalks": 1, "hits": 145, "hitByPitch": 11, "avg": ".255", "atBats": 569, "obp": ".368", "slg": ".424", "ops": ".792", "caughtStealing": 9, "stolenBases": 14, "stolenBasePercentage": ".609", "groundIntoDoublePlay": 12, "numberOfPitches": 2889, "plateAppearances": 682, "totalBases": 241, "rbi": 65, "leftOnBase": 202, "sacBunts": 0, "sacFlies": 7, "babip": ".304", "groundOutsToAirouts": "0.96", "catchersInterference": 0, "atBatsPerHomeRun": "28.45"}}, {"type": "yearByYear", "group": "hitting", "season": "2019", "stats": {"gamesPlayed": 59, "groundOuts": 58, "airOuts": 50, "runs": 45, "doubles": 12, "triples": 1, "homeRuns": 10, "strikeOuts": 55, "baseOnBalls": 43, "intentionalWalks": 0, "hits": 56, "hitByPitch": 0, "avg": ".256", "atBats": 219, "obp": ".378", "slg": ".457", "ops": ".835", "caughtStealing": 1, "stolenBases": 2, "stolenBasePercentage": ".667", "groundIntoDoublePlay": 1, "numberOfPitches": 1165, "plateAppearances": 262, "totalBases": 100, "rbi": 29, "leftOnBase": 53, "sacBunts": 0, "sacFlies": 0, "babip": ".299", "groundOutsToAirouts": "1.16", "catchersInterference": 0, "atBatsPerHomeRun": "21.90"}}, {"type": "yearByYear", "group": "hitting", "season": "2020", "stats": {"gamesPlayed": 57, "groundOuts": 44, "airOuts": 71, "runs": 32, "doubles": 9, "triples": 0, "homeRuns": 10, "strikeOuts": 48, "baseOnBalls": 22, "intentionalWalks": 0, "hits": 55, "hitByPitch": 1, "avg": ".253", "atBats": 217, "obp": ".324", "slg": ".433", "ops": ".757", "caughtStealing": 0, "stolenBases": 4, "stolenBasePercentage": "1.000", "groundIntoDoublePlay": 4, "numberOfPitches": 974, "plateAppearances": 241, "totalBases": 94, "rbi": 34, "leftOnBase": 72, "sacBunts": 0, "sacFlies": 1, "babip": ".281", "groundOutsToAirouts": "0.62", "catchersInterference": 0, "atBatsPerHomeRun": "21.70"}}, {"type": "yearByYear", "group": "hitting", "season": "2021", "stats": {"gamesPlayed": 144, "groundOuts": 120, "airOuts": 130, "runs": 78, "doubles": 24, "triples": 1, "homeRuns": 27, "strikeOuts": 132, "baseOnBalls": 81, "intentionalWalks": 2, "hits": 107, "hitByPitch": 4, "avg": ".222", "atBats": 482, "obp": ".334", "slg": ".444", "ops": ".778", "caughtStealing": 1, "stolenBases": 6, "stolenBasePercentage": ".857", "groundIntoDoublePlay": 10, "numberOfPitches": 2308, "plateAppearances": 574, "totalBases": 214, "rbi": 80, "leftOnBase": 200, "sacBunts": 0, "sacFlies": 7, "babip": ".242", "groundOutsToAirouts": "0.92", "catchersInterference": 0, "atBatsPerHomeRun": "17.85"}}, {"type": "yearByYear", "group": "hitting", "season": "2022", "stats": {"gamesPlayed": 134, "groundOuts": 129, "airOuts": 144, "runs": 66, "doubles": 25, "triples": 0, "homeRuns": 17, "strikeOuts": 124, "baseOnBalls": 57, "intentionalWalks": 1, "hits": 122, "hitByPitch": 4, "avg": ".237", "atBats": 515, "obp": ".316", "slg": ".384", "ops": ".700", "caughtStealing": 6, "stolenBases": 8, "stolenBasePercentage": ".571", "groundIntoDoublePlay": 10, "numberOfPitches": 2364, "plateAppearances": 580, "totalBases": 198, "rbi": 69, "leftOnBase": 226, "sacBunts": 0, "sacFlies": 4, "babip": ".278", "groundOutsToAirouts": "0.90", "catchersInterference": 0, "atBatsPerHomeRun": "30.29"}}, {"type": "yearByYear", "group": "fielding", "season": "2009", "stats": {"gamesPlayed": 108, "gamesStarted": 108, "assists": 10, "putOuts": 263, "errors": 2, "chances": 275, "fielding": ".993", "position": {"code": "8", "name": "Outfielder", "type": "Outfielder", "abbreviation": "CF"}, "rangeFactorPerGame": "2.53", "rangeFactorPer9Inn": "2.58", "innings": "952.2", "games": 108, "doublePlays": 1, "triplePlays": 0, "throwingErrors": 1}}, {"type": "yearByYear", "group": "fielding", "season": "2010", "stats": {"gamesPlayed": 152, "gamesStarted": 152, "assists": 8, "putOuts": 373, "errors": 5, "chances": 386, "fielding": ".987", "position": {"code": "8", "name": "Outfielder", "type": "Outfielder", "abbreviation": "CF"}, "rangeFactorPerGame": "2.51", "rangeFactorPer9Inn": "2.66", "innings": "1290.1", "games": 152, "doublePlays": 2, "triplePlays": 0, "throwingErrors": 2}}, {"type": "yearByYear", "group": "fielding", "season": "2011", "stats": {"gamesPlayed": 155, "gamesStarted": 153, "assists": 9, "putOuts": 414, "errors": 7, "chances": 430, "fielding": ".984", "position": {"code": "8", "name": "Outfielder", "type": "Outfielder", "abbreviation": "CF"}, "rangeFactorPerGame": "2.73", "rangeFactorPer9Inn": "2.81", "innings": "1353.2", "games": 155, "doublePlays": 5, "triplePlays": 0, "throwingErrors": 2}}, {"type": "yearByYear", "group": "fielding", "season": "2011", "stats": {"gamesPlayed": 1, "gamesStarted": 1, "assists": 0, "putOuts": 0, "errors": 0, "chances": 0, "fielding": ".000", "position": {"code": "10", "name": "Designated Hitter", "type": "Hitter", "abbreviation": "DH"}, "rangeFactorPerGame": "0.00", "rangeFactorPer9Inn": "-.--", "innings": "0.0", "games": 1, "doublePlays": 0, "triplePlays": 0, "throwingErrors": 0}}, {"type": "yearByYear", "group": "fielding", "season": "2012", "stats": {"gamesPlayed": 156, "gamesStarted": 156, "assists": 3, "putOuts": 367, "errors": 1, "chances": 371, "fielding": ".997", "position": {"code": "8", "name": "Outfielder", "type": "Outfielder", "abbreviation": "CF"}, "rangeFactorPerGame": "2.37", "rangeFactorPer9Inn": "2.44", "innings": "1364.0", "games": 156, "doublePlays": 1, "triplePlays": 0, "throwingErrors": 0}}, {"type": "yearByYear", "group": "fielding", "season": "2013", "stats": {"gamesPlayed": 155, "gamesStarted": 154, "assists": 11, "putOuts": 321, "errors": 6, "chances": 338, "fielding": ".982", "position": {"code": "8", "name": "Outfielder", "type": "Outfielder", "abbreviation": "CF"}, "rangeFactorPerGame": "2.14", "rangeFactorPer9Inn": "2.17", "innings": "1378.0", "games": 155, "doublePlays": 3, "triplePlays": 0, "throwingErrors": 2}}, {"type": "yearByYear", "group": "fielding", "season": "2014", "stats": {"gamesPlayed": 146, "gamesStarted": 146, "assists": 1, "putOuts": 301, "errors": 6, "chances": 308, "fielding": ".981", "position": {"code": "8", "name": "Outfielder", "type": "Outfielder", "abbreviation": "CF"}, "rangeFactorPerGame": "2.07", "rangeFactorPer9Inn": "2.11", "innings": "1286.0", "games": 146, "doublePlays": 0, "triplePlays": 0, "throwingErrors": 1}}, {"type": "yearByYear", "group": "fielding", "season": "2015", "stats": {"gamesPlayed": 152, "gamesStarted": 151, "assists": 7, "putOuts": 301, "errors": 2, "chances": 310, "fielding": ".994", "position": {"code": "8", "name": "Outfielder", "type": "Outfielder", "abbreviation": "CF"}, "rangeFactorPerGame": "2.03", "rangeFactorPer9Inn": "2.02", "innings": "1374.2", "games": 152, "doublePlays": 2, "triplePlays": 0, "throwingErrors": 1}}, {"type": "yearByYear", "group": "fielding", "season": "2015", "stats": {"gamesPlayed": 3, "gamesStarted": 3, "assists": 0, "putOuts": 0, "errors": 0, "chances": 0, "fielding": ".000", "position": {"code": "10", "name": "Designated Hitter", "type": "Hitter", "abbreviation": "DH"}, "rangeFactorPerGame": "0.00", "rangeFactorPer9Inn": "-.--", "innings": "0.0", "games": 3, "doublePlays": 0, "triplePlays": 0, "throwingErrors": 0}}, {"type": "yearByYear", "group": "fielding", "season": "2016", "stats": {"gamesPlayed": 151, "gamesStarted": 151, "assists": 6, "putOuts": 317, "errors": 3, "chances": 326, "fielding": ".991", "position": {"code": "8", "name": "Outfielder", "type": "Outfielder", "abbreviation": "CF"}, "rangeFactorPerGame": "2.14", "rangeFactorPer9Inn": "2.21", "innings": "1318.0", "games": 151, "doublePlays": 0, "triplePlays": 0, "throwingErrors": 0}}, {"type": "yearByYear", "group": "fielding", "season": "2017", "stats": {"gamesPlayed": 139, "gamesStarted": 139, "assists": 8, "putOuts": 270, "errors": 4, "chances": 282, "fielding": ".986", "position": {"code": "8", "name": "Outfielder", "type": "Outfielder", "abbreviation": "CF"}, "rangeFactorPerGame": "2.00", "rangeFactorPer9Inn": "2.11", "innings": "1188.1", "games": 139, "doublePlays": 2, "triplePlays": 0, "throwingErrors": 0}}, {"type": "yearByYear", "group": "fielding", "season": "2017", "stats": {"gamesPlayed": 13, "gamesStarted": 13, "assists": 1, "putOuts": 20, "errors": 0, "chances": 21, "fielding": "1.000", "position": {"code": "9", "name": "Outfielder", "type": "Outfielder", "abbreviation": "RF"}, "rangeFactorPerGame": "1.62", "rangeFactorPer9Inn": "1.64", "innings": "115.1", "games": 13, "doublePlays": 0, "triplePlays": 0, "throwingErrors": 0}}, {"type": "yearByYear", "group": "fielding", "season": "2017", "stats": {"gamesPlayed": 2, "gamesStarted": 2, "assists": 0, "putOuts": 0, "errors": 0, "chances": 0, "fielding": ".000", "position": {"code": "10", "name": "Designated Hitter", "type": "Hitter", "abbreviation": "DH"}, "rangeFactorPerGame": "0.00", "rangeFactorPer9Inn": "-.--", "innings": "0.0", "games": 2, "doublePlays": 0, "triplePlays": 0, "throwingErrors": 0}}, {"type": "yearByYear", "group": "fielding", "season": "2018", "stats": {"gamesPlayed": 128, "gamesStarted": 127, "assists": 8, "putOuts": 245, "errors": 2, "chances": 255, "fielding": ".992", "position": {"code": "9", "name": "Outfielder", "type": "Outfielder", "abbreviation": "RF"}, "rangeFactorPerGame": "1.98", "rangeFactorPer9Inn": "2.02", "innings": "1125.2", "games": 128, "doublePlays": 1, "triplePlays": 0, "throwingErrors": 0}}, {"type": "yearByYear", "group": "fielding", "season": "2018", "stats": {"gamesPlayed": 1, "gamesStarted": 1, "assists": 0, "putOuts": 0, "errors": 0, "chances": 0, "fielding": ".000", "position": {"code": "10", "name": "Designated Hitter", "type": "Hitter", "abbreviation": "DH"}, "rangeFactorPerGame": "0.00", "rangeFactorPer9Inn": "-.--", "innings": "0.0", "games": 1, "doublePlays": 0, "triplePlays": 0, "throwingErrors": 0}}, {"type": "yearByYear", "group": "fielding", "season": "2018", "stats": {"gamesPlayed": 15, "gamesStarted": 15, "assists": 0, "putOuts": 17, "errors": 0, "chances": 17, "fielding": "1.000", "position": {"code": "9", "name": "Outfielder", "type": "Outfielder", "abbreviation": "RF"}, "rangeFactorPerGame": "1.13", "rangeFactorPer9Inn": "1.30", "innings": "118.0", "games": 15, "doublePlays": 0, "triplePlays": 0, "throwingErrors": 0}}, {"type": "yearByYear", "group": "fielding", "season": "2018", "stats": {"gamesPlayed": 1, "gamesStarted": 1, "assists": 0, "putOuts": 0, "errors": 0, "chances": 0, "fielding": ".000", "position": {"code": "10", "name": "Designated Hitter", "type": "Hitter", "abbreviation": "DH"}, "rangeFactorPerGame": "0.00", "rangeFactorPer9Inn": "-.--", "innings": "0.0", "games": 1, "doublePlays": 0, "triplePlays": 0, "throwingErrors": 0}}, {"type": "yearByYear", "group": "fielding", "season": "2018", "stats": {"gamesPlayed": 12, "gamesStarted": 9, "assists": 0, "putOuts": 17, "errors": 0, "chances": 17, "fielding": "1.000", "position": {"code": "7", "name": "Outfielder", "type": "Outfielder", "abbreviation": "LF"}, "rangeFactorPerGame": "1.42", "rangeFactorPer9Inn": "1.70", "innings": "90.0", "games": 12, "doublePlays": 0, "triplePlays": 0, "throwingErrors": 0}}, {"type": "yearByYear", "group": "fielding", "season": "2018", "stats": {"gamesPlayed": 143, "gamesStarted": 142, "assists": 8, "putOuts": 262, "errors": 2, "chances": 272, "fielding": ".993", "position": {"code": "9", "name": "Outfielder", "type": "Outfielder", "abbreviation": "RF"}, "rangeFactorPerGame": "1.89", "rangeFactorPer9Inn": "1.95", "innings": "1243.2", "games": 143, "doublePlays": 1, "triplePlays": 0, "throwingErrors": 0}}, {"type": "yearByYear", "group": "fielding", "season": "2018", "stats": {"gamesPlayed": 2, "gamesStarted": 2, "assists": 0, "putOuts": 0, "errors": 0, "chances": 0, "fielding": ".000", "position": {"code": "10", "name": "Designated Hitter", "type": "Hitter", "abbreviation": "DH"}, "rangeFactorPerGame": "0.00", "rangeFactorPer9Inn": "-.--", "innings": "0.0", "games": 2, "doublePlays": 0, "triplePlays": 0, "throwingErrors": 0}}, {"type": "yearByYear", "group": "fielding", "season": "2019", "stats": {"gamesPlayed": 52, "gamesStarted": 47, "assists": 2, "putOuts": 79, "errors": 1, "chances": 82, "fielding": ".988", "position": {"code": "7", "name": "Outfielder", "type": "Outfielder", "abbreviation": "LF"}, "rangeFactorPerGame": "1.56", "rangeFactorPer9Inn": "1.81", "innings": "402.1", "games": 52, "doublePlays": 0, "triplePlays": 0, "throwingErrors": 0}}, {"type": "yearByYear", "group": "fielding", "season": "2019", "stats": {"gamesPlayed": 15, "gamesStarted": 10, "assists": 0, "putOuts": 27, "errors": 1, "chances": 28, "fielding": ".964", "position": {"code": "8", "name": "Outfielder", "type": "Outfielder", "abbreviation": "CF"}, "rangeFactorPerGame": "1.80", "rangeFactorPer9Inn": "2.61", "innings": "93.1", "games": 15, "doublePlays": 0, "triplePlays": 0, "throwingErrors": 0}}, {"type": "yearByYear", "group": "fielding", "season": "2019", "stats": {"gamesPlayed": 1, "gamesStarted": 1, "assists": 0, "putOuts": 0, "errors": 0, "chances": 0, "fielding": ".000", "position": {"code": "10", "name": "Designated Hitter", "type": "Hitter", "abbreviation": "DH"}, "rangeFactorPerGame": "0.00", "rangeFactorPer9Inn": "-.--", "innings": "0.0", "games": 1, "doublePlays": 0, "triplePlays": 0, "throwingErrors": 0}}, {"type": "yearByYear", "group": "fielding", "season": "2020", "stats": {"gamesPlayed": 39, "gamesStarted": 36, "assists": 0, "putOuts": 47, "errors": 0, "chances": 47, "fielding": "1.000", "position": {"code": "7", "name": "Outfielder", "type": "Outfielder", "abbreviation": "LF"}, "rangeFactorPerGame": "1.21", "rangeFactorPer9Inn": "1.40", "innings": "302.0", "games": 39, "doublePlays": 0, "triplePlays": 0, "throwingErrors": 0}}, {"type": "yearByYear", "group": "fielding", "season": "2020", "stats": {"gamesPlayed": 16, "gamesStarted": 16, "assists": 0, "putOuts": 0, "errors": 0, "chances": 0, "fielding": ".000", "position": {"code": "10", "name": "Designated Hitter", "type": "Hitter", "abbreviation": "DH"}, "rangeFactorPerGame": "0.00", "rangeFactorPer9Inn": "-.--", "innings": "0.0", "games": 16, "doublePlays": 0, "triplePlays": 0, "throwingErrors": 0}}, {"type": "yearByYear", "group": "fielding", "season": "2021", "stats": {"gamesPlayed": 135, "gamesStarted": 131, "assists": 4, "putOuts": 189, "errors": 4, "chances": 197, "fielding": ".980", "position": {"code": "7", "name": "Outfielder", "type": "Outfielder", "abbreviation": "LF"}, "rangeFactorPerGame": "1.43", "rangeFactorPer9Inn": "1.58", "innings": "1099.0", "games": 135, "doublePlays": 0, "triplePlays": 0, "throwingErrors": 1}}, {"type": "yearByYear", "group": "fielding", "season": "2021", "stats": {"gamesPlayed": 1, "gamesStarted": 1, "assists": 0, "putOuts": 0, "errors": 0, "chances": 0, "fielding": ".000", "position": {"code": "10", "name": "Designated Hitter", "type": "Hitter", "abbreviation": "DH"}, "rangeFactorPerGame": "0.00", "rangeFactorPer9Inn": "-.--", "innings": "0.0", "games": 1, "doublePlays": 0, "triplePlays": 0, "throwingErrors": 0}}, {"type": "yearByYear", "group": "fielding", "season": "2022", "stats": {"gamesPlayed": 31, "gamesStarted": 31, "assists": 0, "putOuts": 53, "errors": 0, "chances": 53, "fielding": "1.000", "position": {"code": "7", "name": "Outfielder", "type": "Outfielder", "abbreviation": "LF"}, "rangeFactorPerGame": "1.71", "rangeFactorPer9Inn": "1.78", "innings": "268.1", "games": 31, "doublePlays": 0, "triplePlays": 0, "throwingErrors": 0}}, {"type": "yearByYear", "group": "fielding", "season": "2022", "stats": {"gamesPlayed": 3, "gamesStarted": 2, "assists": 0, "putOuts": 5, "errors": 0, "chances": 5, "fielding": "1.000", "position": {"code": "8", "name": "Outfielder", "type": "Outfielder", "abbreviation": "CF"}, "rangeFactorPerGame": "1.67", "rangeFactorPer9Inn": "3.46", "innings": "13.0", "games": 3, "doublePlays": 0, "triplePlays": 0, "throwingErrors": 0}}, {"type": "yearByYear", "group": "fielding", "season": "2022", "stats": {"gamesPlayed": 19, "gamesStarted": 16, "assists": 1, "putOuts": 30, "errors": 0, "chances": 31, "fielding": "1.000", "position": {"code": "9", "name": "Outfielder", "type": "Outfielder", "abbreviation": "RF"}, "rangeFactorPerGame": "1.63", "rangeFactorPer9Inn": "1.82", "innings": "153.0", "games": 19, "doublePlays": 0, "triplePlays": 0, "throwingErrors": 0}}, {"type": "yearByYear", "group": "fielding", "season": "2022", "stats": {"gamesPlayed": 82, "gamesStarted": 82, "assists": 0, "putOuts": 0, "errors": 0, "chances": 0, "fielding": ".000", "position": {"code": "10", "name": "Designated Hitter", "type": "Hitter", "abbreviation": "DH"}, "rangeFactorPerGame": "0.00", "rangeFactorPer9Inn": "-.--", "innings": "0.0", "games": 82, "doublePlays": 0, "triplePlays": 0, "throwingErrors": 0}}]}}